worldhello/__init__.py
worldhello-1.0.0.dist-info/METADATA
worldhello-1.0.0.dist-info/WHEEL
worldhello-1.0.0.dist-info/top_level.txt
worldhello-1.0.0.dist-info/RECORD
